onescript_kernel/__init__.py
onescript_kernel/install.py
onescript_kernel/kernel.py
onescript_kernel/kernel_spec/kernel.json
onescript_kernel-1.0.9.dist-info/METADATA
onescript_kernel-1.0.9.dist-info/WHEEL
onescript_kernel-1.0.9.dist-info/entry_points.txt
onescript_kernel-1.0.9.dist-info/top_level.txt
onescript_kernel-1.0.9.dist-info/RECORD
