Metadata-Version: 2.4
Name: onescript-kernel
Version: 1.0.9
Summary: OneScript kernel for Jupyter
Home-page: https://github.com/nkrasnov322/onescript-kernel
Author: Nikolay Krasnov
Author-email: nikolay@krasnov.cf
Requires-Dist: jupyter_client
Requires-Dist: ipykernel
Dynamic: author
Dynamic: author-email
Dynamic: description
Dynamic: description-content-type
Dynamic: home-page
Dynamic: requires-dist
Dynamic: summary
